ifunnyapi/__init__.py
ifunnyapi/api.py
ifunnyapi/auth.py
ifunnyapi/endpoints.py
ifunnyapi/enums.py
ifunnyapi/exceptions.py
ifunnyapi/utils.py
ifunnyapi-0.0.14.dist-info/LICENSE
ifunnyapi-0.0.14.dist-info/METADATA
ifunnyapi-0.0.14.dist-info/WHEEL
ifunnyapi-0.0.14.dist-info/top_level.txt
ifunnyapi-0.0.14.dist-info/RECORD
