Metadata-Version: 2.1
Name: ifunnyapi
Version: 0.0.14
Summary: Interact with iFunny's API
Home-page: https://github.com/EamonTracey/ifunnyapi
Author: Eamon Tracey
License: UNKNOWN
Platform: UNKNOWN
Classifier: Programming Language :: Python :: 3
Classifier: License :: OSI Approved :: MIT License
Classifier: Operating System :: OS Independent
Requires-Python: >=3.6
Requires-Dist: pillow
Requires-Dist: requests
